README.md
setup.cfg
setup.py
synchronized_set/__init__.py
synchronized_set.egg-info/PKG-INFO
synchronized_set.egg-info/SOURCES.txt
synchronized_set.egg-info/dependency_links.txt
synchronized_set.egg-info/top_level.txt